mycalc/calculator.py
chaewon-0.0.1.dist-info/METADATA
chaewon-0.0.1.dist-info/WHEEL
chaewon-0.0.1.dist-info/top_level.txt
chaewon-0.0.1.dist-info/RECORD
