Metadata-Version: 2.1
Name: chaewon
Version: 0.0.1
Summary: nice calculator
Home-page: https://github.com/mikieoo/calc001
Download-URL: https://github.com/mikieoo/calc001/
Author: cwjang
Classifier: Programming Language :: Python :: 3
